query_log_tracer/__init__.py
query_log_tracer/__version__.py
query_log_tracer/trace.py
query_log_tracer-0.0.1.data/scripts/query-log-tracer
tests/__init__.py
tests/test_trace.py
tests/test_version.py
query_log_tracer-0.0.1.dist-info/LICENSE
query_log_tracer-0.0.1.dist-info/METADATA
query_log_tracer-0.0.1.dist-info/WHEEL
query_log_tracer-0.0.1.dist-info/top_level.txt
query_log_tracer-0.0.1.dist-info/RECORD
