Metadata-Version: 2.1
Name: query-log-tracer
Version: 0.0.1
Summary: A Python tool/library that traces a value in MySQL general logs.
Home-page: https://github.com/kotarot/query-log-tracer
Author: Kotaro Terada
Author-email: kotarot@apache.org
License: Apache 2.0
Keywords: python mysql log
Platform: UNKNOWN
Classifier: Development Status :: 4 - Beta
Classifier: Intended Audience :: End Users/Desktop
Classifier: License :: OSI Approved :: Apache Software License
Classifier: Programming Language :: Python :: 3.6
Classifier: Programming Language :: Python :: 3.7
Classifier: Programming Language :: Python :: 3.8
Classifier: Programming Language :: Python :: 3.9
Requires-Dist: sqlparse (<1.0.0,>=0.4.1)
Provides-Extra: dev
Requires-Dist: pytest (<7.0.0,>=6.2.4) ; extra == 'dev'
